freeze_transitive/__init__.py
freeze_transitive/__main__.py
freeze_transitive/api.py
freeze_transitive/errors.py
freeze_transitive/parsers.py
freeze_transitive/schema.py
freeze_transitive/state_cache.py
freeze_transitive-0.0.0a0.dist-info/LICENSE
freeze_transitive-0.0.0a0.dist-info/METADATA
freeze_transitive-0.0.0a0.dist-info/WHEEL
freeze_transitive-0.0.0a0.dist-info/top_level.txt
freeze_transitive-0.0.0a0.dist-info/RECORD
