Metadata-Version: 2.1
Name: freeze-transitive
Version: 0.0.0a0
Summary: Freeze transitive pre-commit dependencies in Python hooks.
Home-page: https://github.com/antonagestam/freeze-transitive/
Author: Anton Agestam
Author-email: git@antonagestam.se
License: BSD 3-Clause License
Project-URL: Source Repository, https://github.com/antonagestam/freeze-transitive/
Classifier: Intended Audience :: Developers
Classifier: Operating System :: OS Independent
Classifier: Programming Language :: Python
Classifier: Programming Language :: Python :: 3
Classifier: Programming Language :: Python :: 3 :: Only
Classifier: Programming Language :: Python :: 3.10
Classifier: Programming Language :: Python :: 3.11
Requires-Python: >=3.10
License-File: LICENSE
Requires-Dist: typing-extensions (>=4.4.0)
Requires-Dist: pyyaml (>=5.1)
